{
    "sliding_window-tfidf-cosine-median_(2,2)-spectral_clustering":{
        "window_size": (20,200),
        "step_size":(10,60),
        'sim_thresh':(0.2,0.9),
        'n_clusters': (10,18)
    },
    'sliding_window-tfidf-cosine-median_(3,3)-spectral_clustering':{
        "window_size": (20,150),
        "step_size":(10,60),
        'sim_thresh':(0.3,0.6),
        'n_clusters': (12,18)
    },
    'sliding_window-tfidf-cosine-None-spectral_clustering':{
        "window_size": (20,150),
        "step_size":(10,60),
        'sim_thresh':(0.3,0.6),
        'n_clusters': (12,18)
    },
    "sliding_window-tf-cosine-median_(2,2)-spectral_clustering":{
        "window_size": (20,200),
        "step_size":(10,60),
        'sim_thresh':(0.3,0.6),
        'n_clusters': (10,18)
    },
    'sliding_window-tf-cosine-median_(3,3)-spectral_clustering':{
        "window_size": (20,150),
        "step_size":(10,60),
        'sim_thresh':(0.3,0.6),
        'n_clusters': (12,18)
    },
    'sliding_window-tf-cosine-None-spectral_clustering':{
        "window_size": (20,150),
        "step_size":(10,60),
        'sim_thresh':(0.3,0.6),
        'n_clusters': (12,18)
    },
	"sliding_window-lda-cosine-median_(2,2)-spectral_clustering":{
        "window_size": (20,150),
        "step_size":(10,60),
        'sim_thresh':(0.3,0.6),
        'n_clusters': (12,18),
		'alpha':(1e-03,1e-06),
		'eta':(0.005,0.005),
		'chunksize':(80,100),
		'minimum_probability':(0,0),
		'passes': (5,7)
    },
	"sliding_window-lda-cosine-median_(3,3)-spectral_clustering":{
        "window_size": (20,150),
        "step_size":(10,60),
        'sim_thresh':(0.3,0.6),
        'n_clusters': (12,18),
		'alpha':(1e-03,1e-06),
		'eta':(0.005,0.005),
		'chunksize':(80,100),
		'minimum_probability':(0,0),
		'passes': (5,7)
    },
	"sliding_window-lda-cosine-median_(4,4)-spectral_clustering":{
        "window_size": (20,150),
        "step_size":(10,60),
        'sim_thresh':(0.3,0.6),
        'n_clusters': (12,18),
		'alpha':(1e-03,1e-06),
		'eta':(0.005,0.0005),
		'chunksize':(60,100),
		'minimum_probability':(0,0),
		'passes': (5,7)
    },
    "sliding_window-lda-jensen_shannon-median_(2,2)-spectral_clustering":{
        "window_size": (20,150),
        "step_size":(10,60),
        'sim_thresh':(0.3,0.6),
        'n_clusters': (12,18),
		'alpha':(1e-03,1e-06),
		'eta':(0.005,0.0005),
		'chunksize':(60,100),
		'minimum_probability':(0,0),
		'passes': (5,7)
    },
	"sliding_window-lda-jensen_shannon-median_(3,3)-spectral_clustering":{
        "window_size": (20,150),
        "step_size":(10,60),
        'sim_thresh':(0.3,0.6),
        'n_clusters': (12,18),
		'alpha':(1e-03,1e-06),
		'eta':(0.005,0.0005),
		'chunksize':(60,100),
		'minimum_probability':(0,0),
		'passes': (5,7)
    },
	"sliding_window-lda-jensen_shannon-median_(4,4)-spectral_clustering":{
        "window_size": (20,150),
        "step_size":(10,60),
        'sim_thresh':(0.3,0.6),
        'n_clusters': (12,18),
		'alpha':(1e-03,1e-06),
		'eta':(0.005,0.0005),
		'chunksize':(60,100),
		'minimum_probability':(0,0),
		'passes': (5,7)
    },
	'sliding_window-do_nothing-wmdistance-median_(2,2)-spectral_clustering':{
        "window_size": (20,150),
        "step_size":(10,60),
        'sim_thresh':(0.3,0.7),
        'n_clusters': (12,18)
    },	
	"audio-tfidf-cosine-median_(2,2)-spectral_clustering":{
        "silence_threshold": (-60,0),
        "slice_length": (10,1000),
        "step_size_audio":(1,1000),
        'sim_thresh':(0.2,0.9),
        'n_clusters': (10,18)
    },
    'audio-tfidf-cosine-median_(3,3)-spectral_clustering':{
        "silence_threshold": (-60,0),
        "slice_length": (10,1000),
        "step_size_audio":(1,1000),
        'sim_thresh':(0.3,0.6),
        'n_clusters': (12,18)
    },
    'audio-tfidf-cosine-None-spectral_clustering':{
        "silence_threshold": (-60,0),
        "slice_length": (10,1000),
        "step_size_audio":(1,1000),
        'sim_thresh':(0.3,0.6),
        'n_clusters': (12,18)
    },
    "audio-tf-cosine-median_(2,2)-spectral_clustering":{
        "silence_threshold": (-60,0),
        "slice_length": (10,1000),
        "step_size_audio":(1,1000),
        'sim_thresh':(0.3,0.6),
        'n_clusters': (10,18)
    },
    'audio-tf-cosine-median_(3,3)-spectral_clustering':{
        "silence_threshold": (-60,0),
        "slice_length": (10,1000),
        "step_size_audio":(1,1000),
        'sim_thresh':(0.3,0.6),
        'n_clusters': (12,18)
    },
    'audio-tf-cosine-None-spectral_clustering':{
        "silence_threshold": (-60,0),
        "slice_length": (10,1000),
        "step_size_audio":(1,1000),
        'sim_thresh':(0.3,0.6),
        'n_clusters': (12,18)
    },
	"audio-lda-cosine-median_(2,2)-spectral_clustering":{
        "silence_threshold": (-60,0),
        "slice_length": (10,1000),
        "step_size_audio":(1,1000),
        'sim_thresh':(0.3,0.6),
        'n_clusters': (12,18),
		'alpha':(1e-03,1e-06),
		'eta':(0.005,0.005),
		'chunksize':(80,100),
		'minimum_probability':(0,0),
		'passes': (5,7)
    },
	"audio-lda-cosine-median_(3,3)-spectral_clustering":{
        "silence_threshold": (-60,0),
        "slice_length": (10,1000),
        "step_size_audio":(1,1000),
        'sim_thresh':(0.3,0.6),
        'n_clusters': (12,18),
		'alpha':(1e-03,1e-06),
		'eta':(0.005,0.005),
		'chunksize':(80,100),
		'minimum_probability':(0,0),
		'passes': (5,7)
    },
	"audio-lda-cosine-median_(4,4)-spectral_clustering":{
        "silence_threshold": (-60,0),
        "slice_length": (10,1000),
        "step_size_audio":(1,1000),
        'sim_thresh':(0.3,0.6),
        'n_clusters': (12,18),
		'alpha':(1e-03,1e-06),
		'eta':(0.005,0.0005),
		'chunksize':(60,100),
		'minimum_probability':(0,0),
		'passes': (5,7)
    },
    "audio-lda-jensen_shannon-median_(2,2)-spectral_clustering":{
        "silence_threshold": (-60,0),
        "slice_length": (10,1000),
        "step_size_audio":(1,1000),
        'sim_thresh':(0.3,0.6),
        'n_clusters': (12,18),
		'alpha':(1e-03,1e-06),
		'eta':(0.005,0.0005),
		'chunksize':(60,100),
		'minimum_probability':(0,0),
		'passes': (5,7)
    },
	"audio-lda-jensen_shannon-median_(3,3)-spectral_clustering":{
        "silence_threshold": (-60,0),
        "slice_length": (10,1000),
        "step_size_audio":(1,1000),
        'sim_thresh':(0.3,0.6),
        'n_clusters': (12,18),
		'alpha':(1e-03,1e-06),
		'eta':(0.005,0.0005),
		'chunksize':(60,100),
		'minimum_probability':(0,0),
		'passes': (5,7)
    },
	"audio-lda-jensen_shannon-median_(4,4)-spectral_clustering":{
        "silence_threshold": (-60,0),
        "slice_length": (10,1000),
        "step_size_audio":(1,1000),
        'sim_thresh':(0.3,0.6),
        'n_clusters': (12,18),
		'alpha':(1e-03,1e-06),
		'eta':(0.005,0.0005),
		'chunksize':(60,100),
		'minimum_probability':(0,0),
		'passes': (5,7)
    },
	'audio-do_nothing-wmdistance-median_(2,2)-spectral_clustering':{
        "silence_threshold": (-60,0),
        "slice_length": (10,1000),
        "step_size_audio":(1,1000),
        'sim_thresh':(0.3,0.7),
        'n_clusters': (12,18)
    },
	"text_changing-tfidf-cosine-median_(2,2)-spectral_clustering":{
        "wanted_frequency":(10,90),
        "wanted_similarity_percent":(50,97),
        'sim_thresh':(0.2,0.9),
        'n_clusters': (10,18)
    },
    'text_changing-tfidf-cosine-median_(3,3)-spectral_clustering':{
        "wanted_frequency":(10,90),
        "wanted_similarity_percent":(50,97),
        'sim_thresh':(0.3,0.6),
        'n_clusters': (12,18)
    },
    'text_changing-tfidf-cosine-None-spectral_clustering':{
        "wanted_frequency":(10,90),
        "wanted_similarity_percent":(50,97),
        'sim_thresh':(0.3,0.6),
        'n_clusters': (12,18)
    },
    "text_changing-tf-cosine-median_(2,2)-spectral_clustering":{
        "wanted_frequency":(10,90),
        "wanted_similarity_percent":(50,97),
        'sim_thresh':(0.3,0.6),
        'n_clusters': (10,18)
    },
    'text_changing-tf-cosine-median_(3,3)-spectral_clustering':{
        "wanted_frequency":(10,90),
        "wanted_similarity_percent":(50,97),
        'sim_thresh':(0.3,0.6),
        'n_clusters': (12,18)
    },
    'text_changing-tf-cosine-None-spectral_clustering':{
        "wanted_frequency":(10,90),
        "wanted_similarity_percent":(50,97),
        'sim_thresh':(0.3,0.6),
        'n_clusters': (12,18)
    },
	"text_changing-lda-cosine-median_(2,2)-spectral_clustering":{
        "wanted_frequency":(10,90),
        "wanted_similarity_percent":(50,97),
        'sim_thresh':(0.3,0.6),
        'n_clusters': (12,18),
		'alpha':(1e-03,1e-06),
		'eta':(0.005,0.005),
		'chunksize':(80,100),
		'minimum_probability':(0,0),
		'passes': (5,7)
    },
	"text_changing-lda-cosine-median_(3,3)-spectral_clustering":{
        "wanted_frequency":(10,90),
        "wanted_similarity_percent":(50,97),
        'sim_thresh':(0.3,0.6),
        'n_clusters': (12,18),
		'alpha':(1e-03,1e-06),
		'eta':(0.005,0.005),
		'chunksize':(80,100),
		'minimum_probability':(0,0),
		'passes': (5,7)
    },
	"text_changing-lda-cosine-median_(4,4)-spectral_clustering":{
        "wanted_frequency":(10,90),
        "wanted_similarity_percent":(50,97),
        'sim_thresh':(0.3,0.6),
        'n_clusters': (12,18),
		'alpha':(1e-03,1e-06),
		'eta':(0.005,0.0005),
		'chunksize':(60,100),
		'minimum_probability':(0,0),
		'passes': (5,7)
    },
    "text_changing-lda-jensen_shannon-median_(2,2)-spectral_clustering":{
        "wanted_frequency":(10,90),
        "wanted_similarity_percent":(50,97),
        'sim_thresh':(0.3,0.6),
        'n_clusters': (12,18),
		'alpha':(1e-03,1e-06),
		'eta':(0.005,0.0005),
		'chunksize':(60,100),
		'minimum_probability':(0,0),
		'passes': (5,7)
    },
	"text_changing-lda-jensen_shannon-median_(3,3)-spectral_clustering":{
        "wanted_frequency":(10,90),
        "wanted_similarity_percent":(50,97),
        'sim_thresh':(0.3,0.6),
        'n_clusters': (12,18),
		'alpha':(1e-03,1e-06),
		'eta':(0.005,0.0005),
		'chunksize':(60,100),
		'minimum_probability':(0,0),
		'passes': (5,7)
    },
	"text_changing-lda-jensen_shannon-median_(4,4)-spectral_clustering":{
        "wanted_frequency":(10,90),
        "wanted_similarity_percent":(50,97),
        'sim_thresh':(0.3,0.6),
        'n_clusters': (12,18),
		'alpha':(1e-03,1e-06),
		'eta':(0.005,0.0005),
		'chunksize':(60,100),
		'minimum_probability':(0,0),
		'passes': (5,7)
    },
	'text_changing-do_nothing-wmdistance-median_(2,2)-spectral_clustering':{
        "wanted_frequency":(10,90),
        "wanted_similarity_percent":(50,97),
        'sim_thresh':(0.3,0.7),
        'n_clusters': (12,18)
    }
}